Pygilent/__init__.py
Pygilent/data/__init__.py
Pygilent/data/stnd_conc_vals.csv
Pygilent/Pygilent.py
Pygilent/stnds.py
Pygilent/uitools.py
pygilent-0.1.2.dist-info/METADATA
pygilent-0.1.2.dist-info/WHEEL
pygilent-0.1.2.dist-info/RECORD
